aioli_rdbms/__init__.py
aioli_rdbms/config.py
aioli_rdbms/manager.py
aioli_rdbms/model.py
aioli_rdbms/proxy.py
aioli_rdbms/service.py
aioli_rdbms-0.3.0.dist-info/LICENSE
aioli_rdbms-0.3.0.dist-info/WHEEL
aioli_rdbms-0.3.0.dist-info/METADATA
aioli_rdbms-0.3.0.dist-info/RECORD
